roksana/__init__.py
roksana/leaderboard.py
roksana/utils.py
roksana/attack_methods/__init__.py
roksana/attack_methods/base_attack.py
roksana/attack_methods/custom_attack.py
roksana/attack_methods/degree.py
roksana/attack_methods/pagerank.py
roksana/attack_methods/random.py
roksana/attack_methods/registry.py
roksana/attack_methods/viking.py
roksana/datasets/__init__.py
roksana/datasets/datasets.py
roksana/evaluation/__init__.py
roksana/evaluation/evaluator.py
roksana/evaluation/metrics.py
roksana/evaluation/utils.py
roksana/search_methods/__init__.py
roksana/search_methods/base_search.py
roksana/search_methods/gat_search.py
roksana/search_methods/gcn_search.py
roksana/search_methods/registry.py
roksana/search_methods/sage_search.py
roksana/search_methods/search_methods.py
ROKSANA-0.2.4.dist-info/LICENSE
ROKSANA-0.2.4.dist-info/METADATA
ROKSANA-0.2.4.dist-info/WHEEL
ROKSANA-0.2.4.dist-info/top_level.txt
ROKSANA-0.2.4.dist-info/RECORD
