Metadata-Version: 2.2
Name: ROKSANA
Version: 0.2.4
Summary: A toolkit for keyword search and attack methods on user-provided datasets.
Home-page: https://github.com/radinhamidi/roksana
Author: Radin Hamidi Rad
Author-email: radin.h@gmail.com
Classifier: Programming Language :: Python :: 3
Classifier: License :: OSI Approved :: MIT License
Classifier: Operating System :: OS Independent
Requires-Python: >=3.9
License-File: LICENSE
Requires-Dist: torch
Requires-Dist: torch-geometric
Dynamic: author
Dynamic: author-email
Dynamic: classifier
Dynamic: description
Dynamic: description-content-type
Dynamic: home-page
Dynamic: requires-dist
Dynamic: requires-python
Dynamic: summary
